bootle.py
bootle-0.1.1.dist-info/LICENSE.txt
bootle-0.1.1.dist-info/WHEEL
bootle-0.1.1.dist-info/METADATA
bootle-0.1.1.dist-info/RECORD
