Metadata-Version: 1.1
Name: bootle
Version: 0.1.1
Summary: “Should array indices start at 0 or 1? My compromise of 0.5 was rejected
Home-page: https://github.com/osteele/bootle
Author: Oliver Steele
Author-email: steele@osteele.com
